virtuals_acp/abis/abi.py
virtuals_acp/abis/abi_v2.py
virtuals_acp/abis/erc20_abi.py
virtuals_acp/abis/flat_token_v2_abi.py
virtuals_acp/abis/job_manager.py
virtuals_acp/abis/single_signer_validation_module_abi.py
virtuals_acp/abis/weth_abi.py
virtuals_acp/account.py
virtuals_acp/alchemy.py
virtuals_acp/client.py
virtuals_acp/configs/configs.py
virtuals_acp/constants.py
virtuals_acp/contract_clients/base_contract_client.py
virtuals_acp/contract_clients/contract_client.py
virtuals_acp/contract_clients/contract_client_v2.py
virtuals_acp/env.py
virtuals_acp/exceptions.py
virtuals_acp/fare.py
virtuals_acp/job.py
virtuals_acp/job_offering.py
virtuals_acp/memo.py
virtuals_acp/models.py
virtuals_acp/utils.py
virtuals_acp/x402.py
virtuals_acp-0.3.18.dist-info/METADATA
virtuals_acp-0.3.18.dist-info/WHEEL
virtuals_acp-0.3.18.dist-info/RECORD
