Metadata-Version: 2.3
Name: virtuals-acp
Version: 0.3.18
Summary: Agent Commerce Protocol Python SDK by Virtuals
Author: Steven Lee Soon Fatt
Author-email: steven@virtuals.io
Requires-Python: >=3.10,<3.13
Classifier: Programming Language :: Python :: 3
Classifier: Programming Language :: Python :: 3.10
Classifier: Programming Language :: Python :: 3.11
Classifier: Programming Language :: Python :: 3.12
Requires-Dist: aiohttp (>=3.11.14,<4.0.0)
Requires-Dist: eth-account (>=0.13.6,<0.14.0)
Requires-Dist: eth-typing (>=5.2.0,<6.0.0)
Requires-Dist: eth-utils (>=5.2.0,<6.0.0)
Requires-Dist: jsonschema (>=4.22.0,<5.0.0)
Requires-Dist: pydantic (>=2.10.6,<3.0.0)
Requires-Dist: pydantic-settings (>=2.0,<3.0)
Requires-Dist: python-socketio (>=5.11.1,<6.0.0)
Requires-Dist: requests (>=2.32.3,<3.0.0)
Requires-Dist: web3 (>=7.4.0,<8.0.0)
Requires-Dist: websocket-client (>=1.7.0,<2.0.0)
